{
    "type" : 5,
    "snippet":
    {
        "query_id":7,
        "work_id":8,
        "query_info":{
            "table_name": ["region"],
            "filtering":[
                
            ],
            "projection": [
                
            ]
        },
        "schema_info":{},
        "index_table_info":{},
        "sst_info":[],
        "wal_info":{},
        "result_info":{
            "table_alias" : "snippet7-8",
            "column_alias": [
                ""
            ]
        }
    }
}